[
  {
    "similar_tables": [
      "agg_daily",
      "agg_hourly"
    ],
    "grouped_by": [
      "brand_id",
      "browser_id",
      "city_id",
      "clicks",
      "conversions",
      "cost",
      "country_id",
      "creative_id",
      "impressions",
      "os_id",
      "postal_code",
      "publisher_id",
      "region_id",
      "spend",
      "views",
      "ymd"
    ]
  },
  {
    "similar_tables": [
      "ad_click",
      "ad_conversion",
      "ad_view"
    ],
    "grouped_by": [
      "ad_request_id",
      "datetime"
    ]
  },
  {
    "similar_tables": [
      "brand",
      "brand_category",
      "browser",
      "city",
      "operating_system",
      "region"
    ],
    "grouped_by": [
      "brand_category_id",
      "id",
      "name"
    ]
  }
]